[
  {
    "Username": "Hayden",
    "UserID": 1256,
    "UserKey": "apple",
    "Entries": [
      {
        "Title": "Amazon",
        "Username": "HaydenCJ",
        "Password": "marbles123",
        "DataScrambled": false
      },
      {
        "Title": "Discord",
        "Username": "Elephant",
        "Password": "cookie123",
        "DataScrambled": false
      },
      {
        "Title": "Google",
        "Username": "haydenJ",
        "Password": "cookie715",
        "DataScrambled": false
      }
    ]
  },
  {
    "Username": "Brooke",
    "UserID": 6711,
    "UserKey": "bee",
    "Entries": [
      {
        "Title": "Amazon",
        "Username": "QueenB",
        "Password": "bee412",
        "DataScrambled": false
      }
    ]
  },
  {
    "Username": "Jessica",
    "UserID": 8750,
    "UserKey": "music",
    "Entries": [
      {
        "Title": "Discord",
        "Username": "jessica",
        "Password": "turtle",
        "DataScrambled": false
      }
    ]
  },
  {
    "Username": "Jason",
    "UserID": 2380,
    "UserKey": "volvo",
    "Entries": [
      {
        "Title": "New Entry",
        "Username": "lazyj",
        "Password": "guitar123",
        "DataScrambled": false
      }
    ]
  },
  {
    "Username": "Andrew",
    "UserID": 3284,
    "UserKey": "bike",
    "Entries": []
  }
]